algokit/__init__.py
algokit/__main__.py
algokit/cli/__init__.py
algokit/cli/bootstrap.py
algokit/cli/completions.py
algokit/cli/config.py
algokit/cli/doctor.py
algokit/cli/explore.py
algokit/cli/goal.py
algokit/cli/init.py
algokit/cli/sandbox.py
algokit/core/__init__.py
algokit/core/atomic_write.py
algokit/core/bootstrap.py
algokit/core/click_extensions.py
algokit/core/conf.py
algokit/core/doctor.py
algokit/core/log_handlers.py
algokit/core/proc.py
algokit/core/questionary_extensions.py
algokit/core/sandbox.py
algokit/core/utils.py
algokit/core/version_prompt.py
algokit_cli-0.1.2.dist-info/entry_points.txt
algokit_cli-0.1.2.dist-info/METADATA
algokit_cli-0.1.2.dist-info/LICENSE
algokit_cli-0.1.2.dist-info/WHEEL
algokit_cli-0.1.2.dist-info/RECORD
